[
  {
    "symbol": "AAPL",
    "price": "",
    "prev_close": "",
    "ts_ms": "",
    "source": "",
    "error": "http 429",
    "category": "CORE"
  },
  {
    "symbol": "MSFT",
    "price": "",
    "prev_close": "",
    "ts_ms": "",
    "source": "",
    "error": "http 429",
    "category": "CORE"
  },
  {
    "symbol": "NVDA",
    "price": "",
    "prev_close": "",
    "ts_ms": "",
    "source": "",
    "error": "http 429",
    "category": "CORE"
  },
  {
    "symbol": "GOOGL",
    "price": 319.95,
    "prev_close": 323.44,
    "ts_ms": 1764190800000,
    "source": "finnhub",
    "error": null,
    "category": "CORE"
  },
  {
    "symbol": "META",
    "price": 633.61,
    "prev_close": 636.22,
    "ts_ms": 1764190800000,
    "source": "finnhub",
    "error": null,
    "category": "CORE"
  },
  {
    "symbol": "AMZN",
    "price": 229.16,
    "prev_close": 229.67,
    "ts_ms": 1764190800000,
    "source": "finnhub",
    "error": null,
    "category": "CORE"
  },
  {
    "symbol": "TSLA",
    "price": 426.58,
    "prev_close": 419.4,
    "ts_ms": 1764190800000,
    "source": "finnhub",
    "error": null,
    "category": "CORE"
  },
  {
    "symbol": "AMD",
    "price": 214.24,
    "prev_close": 206.13,
    "ts_ms": 1764190800000,
    "source": "finnhub",
    "error": null,
    "category": "CORE"
  },
  {
    "symbol": "NFLX",
    "price": 106.14,
    "prev_close": 104.4,
    "ts_ms": 1764190800000,
    "source": "finnhub",
    "error": null,
    "category": "CORE"
  },
  {
    "symbol": "ORCL",
    "price": 204.96,
    "prev_close": 197.03,
    "ts_ms": 1764190800000,
    "source": "finnhub",
    "error": null,
    "category": "CORE"
  },
  {
    "symbol": "IBM",
    "price": 303.21,
    "prev_close": 304.48,
    "ts_ms": 1764190800000,
    "source": "finnhub",
    "error": null,
    "category": "CORE"
  },
  {
    "symbol": "AVGO",
    "price": 397.57,
    "prev_close": 385.03,
    "ts_ms": 1764190800000,
    "source": "finnhub",
    "error": null,
    "category": "CORE"
  },
  {
    "symbol": "QCOM",
    "price": 165.14,
    "prev_close": 163.3,
    "ts_ms": 1764190800000,
    "source": "finnhub",
    "error": null,
    "category": "CORE"
  },
  {
    "symbol": "INTC",
    "price": 36.81,
    "prev_close": 35.83,
    "ts_ms": 1764190800000,
    "source": "finnhub",
    "error": null,
    "category": "CORE"
  },
  {
    "symbol": "NOW",
    "price": 802.72,
    "prev_close": 825.31,
    "ts_ms": 1764190800000,
    "source": "finnhub",
    "error": null,
    "category": "CORE"
  },
  {
    "symbol": "COIN",
    "price": 264.97,
    "prev_close": 254.12,
    "ts_ms": 1764190800000,
    "source": "finnhub",
    "error": null,
    "category": "CORE"
  },
  {
    "symbol": "PLTR",
    "price": 165.77,
    "prev_close": 163.55,
    "ts_ms": 1764190800000,
    "source": "finnhub",
    "error": null,
    "category": "CORE"
  },
  {
    "symbol": "MU",
    "price": 230.26,
    "prev_close": 224.53,
    "ts_ms": 1764190800000,
    "source": "finnhub",
    "error": null,
    "category": "CORE"
  },
  {
    "symbol": "CRWD",
    "price": 501.54,
    "prev_close": 512.34,
    "ts_ms": 1764190800000,
    "source": "finnhub",
    "error": null,
    "category": "CORE"
  },
  {
    "symbol": "BBAI",
    "price": 6.02,
    "prev_close": 6.19,
    "ts_ms": 1764190800000,
    "source": "finnhub",
    "error": null,
    "category": "CORE"
  },
  {
    "symbol": "RGTI",
    "price": 25.57,
    "prev_close": 26.08,
    "ts_ms": 1764190800000,
    "source": "finnhub",
    "error": null,
    "category": "CORE"
  },
  {
    "symbol": "INSM",
    "price": 204.51,
    "prev_close": 209.02,
    "ts_ms": 1764190800000,
    "source": "finnhub",
    "error": null,
    "category": "CORE"
  },
  {
    "symbol": "OPEN",
    "price": 7.78,
    "prev_close": 7.74,
    "ts_ms": 1764190800000,
    "source": "finnhub",
    "error": null,
    "category": "CORE"
  },
  {
    "symbol": "HOOD",
    "price": 128.2,
    "prev_close": 115.57,
    "ts_ms": 1764190800000,
    "source": "finnhub",
    "error": null,
    "category": "CORE"
  },
  {
    "symbol": "AC",
    "price": "",
    "prev_close": "",
    "ts_ms": "",
    "source": "",
    "error": "no_price",
    "category": "CORE"
  },
  {
    "symbol": "CHPT",
    "price": 7.93,
    "prev_close": 7.78,
    "ts_ms": 1764190800000,
    "source": "finnhub",
    "error": null,
    "category": "CORE"
  },
  {
    "symbol": "ALGS",
    "price": 9.86,
    "prev_close": 9.66,
    "ts_ms": 1764190800000,
    "source": "finnhub",
    "error": null,
    "category": "CORE"
  },
  {
    "symbol": "JPM",
    "price": 307.64,
    "prev_close": 303.0,
    "ts_ms": 1764190800000,
    "source": "finnhub",
    "error": null,
    "category": "CORE"
  },
  {
    "symbol": "BAC",
    "price": 52.99,
    "prev_close": 52.48,
    "ts_ms": 1764190800000,
    "source": "finnhub",
    "error": null,
    "category": "CORE"
  },
  {
    "symbol": "GS",
    "price": 816.01,
    "prev_close": 802.32,
    "ts_ms": 1764190800000,
    "source": "finnhub",
    "error": null,
    "category": "CORE"
  },
  {
    "symbol": "MS",
    "price": 167.94,
    "prev_close": 165.43,
    "ts_ms": 1764190800000,
    "source": "finnhub",
    "error": null,
    "category": "CORE"
  },
  {
    "symbol": "WFC",
    "price": 85.56,
    "prev_close": 85.1,
    "ts_ms": 1764190800000,
    "source": "finnhub",
    "error": null,
    "category": "CORE"
  },
  {
    "symbol": "XOM",
    "price": 114.77,
    "prev_close": 114.51,
    "ts_ms": 1764190800000,
    "source": "finnhub",
    "error": null,
    "category": "CORE"
  },
  {
    "symbol": "CVX",
    "price": 149.51,
    "prev_close": 148.53,
    "ts_ms": 1764190800000,
    "source": "finnhub",
    "error": null,
    "category": "CORE"
  },
  {
    "symbol": "COP",
    "price": 87.09,
    "prev_close": 86.62,
    "ts_ms": 1764190800000,
    "source": "finnhub",
    "error": null,
    "category": "CORE"
  },
  {
    "symbol": "SLB",
    "price": 35.66,
    "prev_close": 35.9,
    "ts_ms": 1764190800000,
    "source": "finnhub",
    "error": null,
    "category": "CORE"
  },
  {
    "symbol": "CAT",
    "price": 573.73,
    "prev_close": 566.61,
    "ts_ms": 1764190800000,
    "source": "finnhub",
    "error": null,
    "category": "CORE"
  },
  {
    "symbol": "BA",
    "price": 186.92,
    "prev_close": 182.44,
    "ts_ms": 1764190800000,
    "source": "finnhub",
    "error": null,
    "category": "CORE"
  },
  {
    "symbol": "GE",
    "price": 296.62,
    "prev_close": 293.44,
    "ts_ms": 1764190800000,
    "source": "finnhub",
    "error": null,
    "category": "CORE"
  },
  {
    "symbol": "HON",
    "price": 189.99,
    "prev_close": 191.02,
    "ts_ms": 1764190800000,
    "source": "finnhub",
    "error": null,
    "category": "CORE"
  },
  {
    "symbol": "UNH",
    "price": 329.71,
    "prev_close": 326.28,
    "ts_ms": 1764190800000,
    "source": "finnhub",
    "error": null,
    "category": "CORE"
  },
  {
    "symbol": "JNJ",
    "price": 207.56,
    "prev_close": 206.67,
    "ts_ms": 1764190800000,
    "source": "finnhub",
    "error": null,
    "category": "CORE"
  },
  {
    "symbol": "PFE",
    "price": 25.71,
    "prev_close": 25.72,
    "ts_ms": 1764190800000,
    "source": "finnhub",
    "error": null,
    "category": "CORE"
  },
  {
    "symbol": "MRK",
    "price": 104.63,
    "prev_close": 105.66,
    "ts_ms": 1764190800000,
    "source": "finnhub",
    "error": null,
    "category": "CORE"
  },
  {
    "symbol": "LLY",
    "price": 1104.34,
    "prev_close": 1109.94,
    "ts_ms": 1764190800000,
    "source": "finnhub",
    "error": null,
    "category": "CORE"
  },
  {
    "symbol": "PG",
    "price": 148.25,
    "prev_close": 148.49,
    "ts_ms": 1764190800000,
    "source": "finnhub",
    "error": null,
    "category": "CORE"
  },
  {
    "symbol": "KO",
    "price": 72.88,
    "prev_close": 72.61,
    "ts_ms": 1764190800000,
    "source": "finnhub",
    "error": null,
    "category": "CORE"
  },
  {
    "symbol": "PEP",
    "price": 147.98,
    "prev_close": 146.11,
    "ts_ms": 1764190800000,
    "source": "finnhub",
    "error": null,
    "category": "CORE"
  },
  {
    "symbol": "MCD",
    "price": 312.4,
    "prev_close": 310.45,
    "ts_ms": 1764190800000,
    "source": "finnhub",
    "error": null,
    "category": "CORE"
  },
  {
    "symbol": "NKE",
    "price": 64.33,
    "prev_close": 63.68,
    "ts_ms": 1764190800000,
    "source": "finnhub",
    "error": null,
    "category": "CORE"
  },
  {
    "symbol": "COST",
    "price": 908.26,
    "prev_close": 894.33,
    "ts_ms": 1764190800000,
    "source": "finnhub",
    "error": null,
    "category": "CORE"
  },
  {
    "symbol": "SPY",
    "price": 679.68,
    "prev_close": 675.02,
    "ts_ms": 1764190800000,
    "source": "finnhub",
    "error": null,
    "category": "CORE"
  },
  {
    "symbol": "QQQ",
    "price": 614.27,
    "prev_close": 608.89,
    "ts_ms": 1764190800000,
    "source": "finnhub",
    "error": null,
    "category": "CORE"
  },
  {
    "symbol": "DIA",
    "price": 474.35,
    "prev_close": 471.18,
    "ts_ms": 1764190800000,
    "source": "finnhub",
    "error": null,
    "category": "CORE"
  },
  {
    "symbol": "IWM",
    "price": 247.3,
    "prev_close": 245.13,
    "ts_ms": 1764190800000,
    "source": "finnhub",
    "error": null,
    "category": "CORE"
  },
  {
    "symbol": "VIX",
    "price": "",
    "prev_close": "",
    "ts_ms": "",
    "source": "",
    "error": "no_price",
    "category": "CORE"
  }
]